Workbook

Sheet INSTRUÇÕES
A1: COMO USAR ESTA PLANILHA
A3: PASSO 1: PREENCHIMENTO DIÁRIO
A4: • Abra a aba 'ACOMPANHAMENTO DIÁRIO'
A5: • Na coluna 'Valor Real (R$)' coloque quanto você REALMENTE PAGOU
A6: • A planilha calcula automaticamente a diferença
A8: PASSO 2: ANALISAR RESULTADOS
A9: • Coluna 'Diferença': mostra se gastos foram MAIORES ou MENORES
A10: • Coluna 'Variação (%)': percentual de aumento ou redução
A11: • Coluna 'Status': ✓ OK (dentro do planejado) ou ⚠ AUMENTO (acima)
A13: PASSO 3: ACOMPANHAR TENDÊNCIAS
A14: • Use a aba 'RESUMO MENSAL' para acompanhar semana a semana
A15: • Identifique quais contas estão aumentando mais
... A27: ✓ Use para negociar descontos com fornecedores

Sheet ACOMPANHAMENTO DIÁRIO
A1: ACOMPANHAMENTO DIÁRIO - FLUXO DE CAIXA
A2: Data: 07/06/2026
A4: Nº | B4: Descrição | C4: Valor Fixo (R$) | D4: Valor Real (R$) | E4: Diferença (R$) | F4: Variação (%) | G4: Status
A5: 1 | B5: Insumos 40% | C5: 2600 | E5: =D5-C5 | F5: =IF(C5=0,0,(D5-C5)/C5*100) | G5: =IF(D5="","-",IF(D5<=C5,"✓ OK","⚠ AUMENTO"))
A6: 2 | B6: Folha doméstica | C6: 126.03 | E6: =D6-C6 | F6: =IF(C6=0,0,(D6-C6)/C6*100) | G6: =IF(D6="","-",IF(D6<=C6,"✓ OK","⚠ AUMENTO"))
A7: 3 | B7: Energia loja | C7: 211.36 | E7: =D7-C7 | F7: =IF(C7=0,0,(D7-C7)/C7*100) | G7: =IF(D7="","-",IF(D7<=C7,"✓ OK","⚠ AUMENTO"))
A8: 4 | B8: Deposito escola | C8: 233.85 | E8: =D8-C8 | F8: =IF(C8=0,0,(D8-C8)/C8*100) | G8: =IF(D8="","-",IF(D8<=C8,"✓ OK","⚠ AUMENTO"))
A9: 5 | B9: Macapá Máquinas | C9: 250 | E9: =D9-C9 | F9: =IF(C9=0,0,(D9-C9)/C9*100) | G9: =IF(D9="","-",IF(D9<=C9,"✓ OK","⚠ AUMENTO"))
A10: 6 | B10: Energia residencial | C10: 45.45 | E10: =D10-C10 | F10: =IF(C10=0,0,(D10-C10)/C10*100) | G10: =IF(D10="","-",IF(D10<=C10,"✓ OK","⚠ AUMENTO"))
A11: 7 | B11: Plano de saúde | C11: 300 | E11: =D11-C11 | F11: =IF(C11=0,0,(D11-C11)/C11*100) | G11: =IF(D11="","-",IF(D11<=C11,"✓ OK","⚠ AUMENTO"))
A12: 8 | B12: Condomínio | C12: 17.27 | E12: =D12-C12 | F12: =IF(C12=0,0,(D12-C12)/C12*100) | G12: =IF(D12="","-",IF(D12<=C12,"✓ OK","⚠ AUMENTO"))
A13: 9 | B13: Aluguel Dr. Rodrigo | C13: 239.82 | E13: =D13-C13 | F13: =IF(C13=0,0,(D13-C13)/C13*100) | G13: =IF(D13="","-",IF(D13<=C13,"✓ OK","⚠ AUMENTO"))
A14: 10 | B14: Dedetização | C14: 15.91 | E14: =D14-C14 | F14: =IF(C14=0,0,(D14-C14)/C14*100) | G14: =IF(D14="","-",IF(D14<=C14,"✓ OK","⚠ AUMENTO"))
A15: 11 | B15: Segurança | C15: 31.36 | E15: =D15-C15 | F15: =IF(C15=0,0,(D15-C15)/C15*100) | G15: =IF(D15="","-",IF(D15<=C15,"✓ OK","⚠ AUMENTO"))
A16: 12 | B16: Internet | C16: 27.27 | E16: =D16-C16 | F16: =IF(C16=0,0,(D16-C16)/C16*100) | G16: =IF(D16="","-",IF(D16<=C16,"✓ OK","⚠ AUMENTO"))
... A25: 21 | B25: Imposto Simples Nacional | C25: 204.55 | E25: =D25-C25 | F25: =IF(C25=0,0,(D25-C25)/C25*100) | G25: =IF(D25="","-",IF(D25<=C25,"✓ OK","⚠ AUMENTO"))
A26: TOTAL | C26: =SUM(C5:C25) | D26: =SUM(D5:D25) | E26: =D26-C26 | F26: =IF(C26=0,0,(D26-C26)/C26*100)

Sheet RESUMO MENSAL
A1: RESUMO MENSAL - ANÁLISE DE CUSTOS
A3: Semana | B3: Custo Fixo Planejado | C3: Custo Real | D3: Diferença | E3: Variação (%) | F3: Status
A4: Semana 1 | B4: =ACOMPANHAMENTO DIÁRIO!C4:C4 | D4: =C4-B4 | E4: =IF(B4=0,0,(C4-B4)/B4*100) | F4: =IF(C4="","-",IF(C4<=B4,"✓","⚠"))
A5: Semana 2 | B5: =ACOMPANHAMENTO DIÁRIO!C5:C5 | D5: =C5-B5 | E5: =IF(B5=0,0,(C5-B5)/B5*100) | F5: =IF(C5="","-",IF(C5<=B5,"✓","⚠"))
A6: Semana 3 | B6: =ACOMPANHAMENTO DIÁRIO!C6:C6 | D6: =C6-B6 | E6: =IF(B6=0,0,(C6-B6)/B6*100) | F6: =IF(C6="","-",IF(C6<=B6,"✓","⚠"))
A7: Semana 4 | B7: =ACOMPANHAMENTO DIÁRIO!C7:C7 | D7: =C7-B7 | E7: =IF(B7=0,0,(C7-B7)/B7*100) | F7: =IF(C7="","-",IF(C7<=B7,"✓","⚠"))
A8: Semana 5 | B8: =ACOMPANHAMENTO DIÁRIO!C8:C8 | D8: =C8-B8 | E8: =IF(B8=0,0,(C8-B8)/B8*100) | F8: =IF(C8="","-",IF(C8<=B8,"✓","⚠"))
